clickable_igloo/__init__.py
clickable_igloo-1.1.dist-info/METADATA
clickable_igloo-1.1.dist-info/WHEEL
clickable_igloo-1.1.dist-info/entry_points.txt
clickable_igloo-1.1.dist-info/top_level.txt
clickable_igloo-1.1.dist-info/RECORD
