Metadata-Version: 2.1
Name: clickable-igloo
Version: 1.1
Summary: Igloo helpers for clickable.
Home-page: https://github.com/lalmeras/clickable_igloo
Author: Laurent Almeras
Author-email: lalmeras@gmail.com
License: BSD license
Keywords: clickable
Platform: UNKNOWN
Classifier: Development Status :: 2 - Pre-Alpha
Classifier: Intended Audience :: Developers
Classifier: License :: OSI Approved :: BSD License
Classifier: Natural Language :: English
Classifier: Programming Language :: Python :: 3
Classifier: Programming Language :: Python :: 3.6
Classifier: Programming Language :: Python :: 3.7
Classifier: Programming Language :: Python :: 3.8
Classifier: Programming Language :: Python :: 3.9
Requires-Python: >=3.6
Requires-Dist: clickable (>=1.5)
